setup.py
jb6/__init__.py
jb6.egg-info/PKG-INFO
jb6.egg-info/SOURCES.txt
jb6.egg-info/dependency_links.txt
jb6.egg-info/requires.txt
jb6.egg-info/top_level.txt
jb6/src/__init__.py
jb6/src/ai/QwenAi.py
jb6/src/ai/__init__.py
jb6/src/core/__init__.py
jb6/src/core/useBloomFilter.py
jb6/src/core/usePath.py
jb6/src/core/useTo.py
jb6/src/dict/__init__.py
jb6/src/dict/useDict.py
jb6/src/tools/__init__.py
jb6/src/tools/tools.py