Metadata-Version: 2.4
Name: jb6
Version: 0.0.22
Summary: jb6自用
Author: jb6
License: MIT Licence
Keywords: pip,SongUtils
Platform: any
Requires-Python: >=3.8
Requires-Dist: zhon
Requires-Dist: motor
Requires-Dist: typing
Requires-Dist: loguru
Requires-Dist: pymongo
Requires-Dist: curl_cffi
Requires-Dist: json_repair
Requires-Dist: python-magic
Requires-Dist: python-magic-bin
Dynamic: author
Dynamic: description
Dynamic: keywords
Dynamic: license
Dynamic: platform
Dynamic: requires-dist
Dynamic: requires-python
Dynamic: summary
